haros_plugin_model_ged/__init__.py
haros_plugin_model_ged/graph_diff.py
haros_plugin_model_ged/graph_matching.py
haros_plugin_model_ged/nx_patch.py
haros_plugin_model_ged/output_format.py
haros_plugin_model_ged/plugin.py
haros_plugin_model_ged/plugin.yaml
haros_plugin_model_ged-0.2.1.dist-info/LICENSE
haros_plugin_model_ged-0.2.1.dist-info/METADATA
haros_plugin_model_ged-0.2.1.dist-info/WHEEL
haros_plugin_model_ged-0.2.1.dist-info/top_level.txt
haros_plugin_model_ged-0.2.1.dist-info/RECORD
